{
    "rlt": 0,
    "type": "praise",
    "id": "a110c23c35c44cf4aff2a75cae9d4cdc",
    "startTime": "2017-02-08 14:53:58.0",
    "endTime": "2017-02-08 14:58:17.0",
    "totalPage": 18,
    "data": [
        {
            "mId": "a110c23c35c44cf4aff2a75cae9d4cdc",
            "activityId": "bdef6d43fc504087b8ef074c66568af3",
            "mName": "活动20170208145359",
            "startTime": "2017-02-08 14:53:58",
            "endTime": "2017-02-08 14:58:17",
            "sendType": "c",
            "fullType": "0",
            "fullNum": 0,
            "optLimit": "0",
            "praiseTnum": 10,
            "praiseWLimit": 10,
            "shaituLimit": "",
            "filterKeyword": "系统默认评价,很差,骗人,垃圾,失望,无奈,上当,拙劣,烂,坑爹,质量太差,难看,很破,伤心,再也不来,不值这个价,质量差,质量不行,慎重,太次,粗糙,郁闷,可恶,以防受骗,气人,不敢恭维,太假,不是一般差,差评,中评,便宜没好货,褪色,瑕疵",
            "taobaoId": "749864544",
            "addTime": "2017-02-08 14:56:30",
            "status": 9,
            "goodsid": "",
            "drawNum": 10,
            "marketingType": "praise",
            "goodsType": "1",
            "marketingExplain": "",
            "filterKeyword2": ""
        },
        {
            "mId": "4a2d0dc8ac91456182e4c38a1f548ae0",
            "activityId": "d71fe110f38541e799b4853c5f0cd287",
            "mName": "活动20170206112434",
            "startTime": "2017-02-06 11:24:34",
            "endTime": "2017-02-08 14:36:13",
            "sendType": "p",
            "taobaoId": "749864544",
            "addTime": "2017-02-06 11:25:05",
            "status": 9,
            "drawNum": 0,
            "marketingType": "drainage",
            "marketingExplain": "本店于2017-02-06 11:24:34 至 2017-02-09 11:24:34 期间开展抽奖活动！\r\n感恩回馈,人人有奖！具体的抽奖条件请查看'抽奖条件'说明。\r\n[奖品发放规则]\r\n、手机流量奖品：会发放到淘宝帐户上，请在我的淘宝我的卡券包中查看。\r\n、话费奖品：直接充值到淘宝网内登记的手机号码上。"
        },
        {
            "mId": "c8748142b305433e88652a4d9fca4d52",
            "activityId": "28bc594fc9d64dc284a34b79ef9b3132",
            "mName": "活动20170119182222",
            "startTime": "2017-01-19 18:22:20",
            "endTime": "2017-01-21 18:22:20",
            "sendType": "p",
            "taobaoId": "749864544",
            "addTime": "2017-01-19 18:23:05",
            "status": 9,
            "drawNum": 0,
            "marketingType": "drainage",
            "marketingExplain": "本店于2017-01-19 18:22:20 至 2017-01-21 18:22:20 期间开展抽奖活动！\r\n感恩回馈,人人有奖！具体的抽奖条件请查看'抽奖条件'说明。\r\n[奖品发放规则]\r\n、手机流量奖品：会发放到淘宝帐户上，请在我的淘宝我的卡券包中查看。\r\n、话费奖品：直接充值到淘宝网内登记的手机号码上。"
        },
        {
            "mId": "be1b8fc01dd24cde826f4ec7835a027d",
            "activityId": "9d7e93c8f98a4b4baca6ded8c04a094e",
            "mName": "活动20170113170149",
            "startTime": "2017-01-13 17:01:51",
            "endTime": "2017-01-16 17:01:51",
            "sendType": "p",
            "taobaoId": "749864544",
            "addTime": "2017-01-13 17:03:05",
            "status": 9,
            "drawNum": 0,
            "marketingType": "drainage",
            "marketingExplain": "本店于2017-01-13 17:01:51 至 2017-01-16 17:01:51 期间开展抽奖活动！\r\n感恩回馈,人人有奖！具体的抽奖条件请查看'抽奖条件'说明。\r\n[奖品发放规则]\r\n、手机流量奖品：会发放到淘宝帐户上，请在我的淘宝我的卡券包中查看。\r\n、话费奖品：直接充值到淘宝网内登记的手机号码上。"
        },
        {
            "mId": "4191a076fc65412ebb6dd3705f68dc88",
            "activityId": "7261f72cd5bc4649841199d1118c1b4e",
            "mName": "活动20161229152706",
            "startTime": "2017-01-03 14:50:26",
            "endTime": "2017-01-03 14:55:26",
            "sendType": "c",
            "fullType": "0",
            "fullNum": 0,
            "optLimit": "0",
            "praiseTnum": 15,
            "praiseWLimit": 10,
            "shaituLimit": "",
            "filterKeyword": "系统默认好评,很差,骗人,垃圾,失望,无奈,上当,拙劣,烂,坑爹,质量太差,难看,很破,伤心,再也不来,不值这个价,质量差,质量不行,慎重,太次,粗糙,郁闷,可恶,以防受骗,气人,不敢恭维,太假,不是一般差,差评,中评,便宜没好货,褪色,瑕疵",
            "taobaoId": "749864544",
            "addTime": "2017-01-03 14:50:49",
            "status": 9,
            "goodsid": "",
            "drawNum": 1,
            "marketingType": "praise",
            "goodsType": "1",
            "marketingExplain": "",
            "filterKeyword2": "",
            "marketingDrawNum": 0,
            "marketingDrawTimes": 0,
            "marketingWinnersHead": "中奖名单显示",
            "marketingNoWinners": "中奖名单显示",
            "marketingIsUpdate": "0"
        }
    ],
    "totalRecord": 87,
    "curPage": 8,
    "urls": "http://container.api.taobao.com/container?appkey=21227587&envMode=prod&seller_nick=杭州佑软科技有限公司&module_width=150&shop_id=69589101",
    "isvip": true,
    "sta": "9"
}